core/__init__.py
core/cli.py
core/config.py
core/controller.py
modules/__init__.py
modules/admin.py
modules/ddos.py
modules/gf.py
modules/portscan.py
modules/securitychecker.py
modules/subdomain.py
modules/urlnumeration.py
modules/webscan.py
loly_framework-1.0.0.dist-info/LICENSE
loly_framework-1.0.0.dist-info/METADATA
loly_framework-1.0.0.dist-info/WHEEL
loly_framework-1.0.0.dist-info/entry_points.txt
loly_framework-1.0.0.dist-info/top_level.txt
loly_framework-1.0.0.dist-info/RECORD
