Metadata-Version: 2.1
Name: loly-framework
Version: 1.0.0
Summary: A security framework for testing web applications.
Home-page: https://github.com/hemaabokila/loly_framework
Author: Ibrahem Abo Kila
Author-email: ibrahemabokila@gmail.com
License: MIT
Classifier: Programming Language :: Python :: 3
Classifier: License :: OSI Approved :: MIT License
Classifier: Operating System :: OS Independent
Requires-Python: >=3.6
License-File: LICENSE
Requires-Dist: requests
Requires-Dist: beautifulsoup4
Requires-Dist: cmd2
Requires-Dist: colorama
Requires-Dist: dnspython
Requires-Dist: asyncio
Requires-Dist: rich
